flask_plus/__init__.py
flask_plus/app.py
flask_plus/config.py
flask_plus/exception.py
flask_plus/exts.py
flask_plus/field.py
flask_plus/parse.py
flask_plus/response.py
flask_plus/server.py
flask_plus/ext/__init__.py
flask_plus/ext/auth_header.py
flask_plus/ext/file_logging.py
flask_plus/ext/kong_header.py
flask_plus/ext/minio_hash_storage.py
flask_plus/ext/minio_storage.py
flask_plus/ext/mongo.py
flask_plus/ext/mongo_logging.py
flask_plus/ext/redis.py
flask_plus/ext/remote_config.py
flask_plus/starter/__init__.py
flask_plus/starter/daemon.py
flask_plus/starter/server.py
flask_plus/starter/util.py
FlaskPlus-0.9.dist-info/LICENSE
FlaskPlus-0.9.dist-info/METADATA
FlaskPlus-0.9.dist-info/WHEEL
FlaskPlus-0.9.dist-info/entry_points.txt
FlaskPlus-0.9.dist-info/top_level.txt
FlaskPlus-0.9.dist-info/RECORD
