Metadata-Version: 2.1
Name: FlaskPlus
Version: 0.9
Summary: Many powerful extensions for flask.
Home-page: https://github.com/Leon14451/flaskplus
Author: Leon
Author-email: areuleon@gmail.com
License: BSD
Project-URL: Documentation, https://github.com/Leon14451/flaskplus
Project-URL: Code, https://github.com/Leon14451/flaskplus
Platform: any
Classifier: Development Status :: 5 - Production/Stable
Classifier: Environment :: Web Environment
Classifier: Framework :: Flask
Classifier: Intended Audience :: Developers
Classifier: License :: OSI Approved :: BSD License
Classifier: Operating System :: OS Independent
Classifier: Programming Language :: Python
Classifier: Programming Language :: Python :: 3
Classifier: Programming Language :: Python :: 3.5
Classifier: Programming Language :: Python :: 3.6
Classifier: Programming Language :: Python :: 3.7
Classifier: Topic :: Internet :: WWW/HTTP :: Dynamic Content
Classifier: Topic :: Internet :: WWW/HTTP :: WSGI :: Application
Classifier: Topic :: Software Development :: Libraries :: Application Frameworks
Classifier: Topic :: Software Development :: Libraries :: Python Modules
Requires-Python: >=2.7,!=3.0.*,!=3.1.*,!=3.2.*,!=3.3.*
Requires-Dist: flask (>=1.0.2)
Requires-Dist: ujson (>=1.35)
Requires-Dist: pymongo (>=3.7.2)
Provides-Extra: all
Requires-Dist: redis ; extra == 'all'
Requires-Dist: requests ; extra == 'all'
Requires-Dist: gunicorn ; extra == 'all'
Requires-Dist: minio ; extra == 'all'
